rosdoc2/__init__.py
rosdoc2/main.py
rosdoc2/slugify.py
rosdoc2/verbs/__init__.py
rosdoc2/verbs/build/__init__.py
rosdoc2/verbs/build/build_context.py
rosdoc2/verbs/build/builder.py
rosdoc2/verbs/build/collect_inventory_files.py
rosdoc2/verbs/build/collect_tag_files.py
rosdoc2/verbs/build/create_format_map_from_package.py
rosdoc2/verbs/build/generate_interface_docs.py
rosdoc2/verbs/build/impl.py
rosdoc2/verbs/build/include_user_docs.py
rosdoc2/verbs/build/inspect_package_for_settings.py
rosdoc2/verbs/build/parse_rosdoc2_yaml.py
rosdoc2/verbs/build/standard_documents.py
rosdoc2/verbs/build/builders/__init__.py
rosdoc2/verbs/build/builders/doxygen_builder.py
rosdoc2/verbs/build/builders/index.rst.jinja
rosdoc2/verbs/build/builders/sphinx_builder.py
rosdoc2/verbs/default_config/__init__.py
rosdoc2/verbs/default_config/impl.py
rosdoc2/verbs/open/__init__.py
rosdoc2/verbs/open/impl.py
rosdoc2-0.2.1.dist-info/LICENSE
rosdoc2-0.2.1.dist-info/METADATA
rosdoc2-0.2.1.dist-info/WHEEL
rosdoc2-0.2.1.dist-info/entry_points.txt
rosdoc2-0.2.1.dist-info/top_level.txt
rosdoc2-0.2.1.dist-info/RECORD
