Metadata-Version: 2.1
Name: rosdoc2
Version: 0.2.1
Summary: Command line tool to build documentation for ROS packages.
Home-page: https://github.com/ros-infrastructure/rosdoc2
Author: William Woodall
Author-email: william@openrobotics.org
Maintainer: William Woodall
Maintainer-email: william@openrobotics.org
License: Apache License, Version 2.0
Project-URL: GitHub, https://github.com/ros-infrastructure/rosdoc2
Keywords: rosdoc2
Platform: UNKNOWN
Classifier: Development Status :: 4 - Beta
Classifier: Environment :: Console
Classifier: Intended Audience :: Developers
Classifier: License :: OSI Approved :: Apache Software License
Classifier: Operating System :: MacOS
Classifier: Operating System :: Microsoft :: Windows
Classifier: Operating System :: POSIX
Classifier: Programming Language :: Python
Classifier: Topic :: Software Development :: Documentation
Requires-Python: >=3.6
Requires-Dist: Jinja2
Requires-Dist: breathe
Requires-Dist: catkin-pkg
Requires-Dist: exhale
Requires-Dist: myst-parser
Requires-Dist: osrf-pycommon
Requires-Dist: pyyaml
Requires-Dist: setuptools (>=40.6.0)
Requires-Dist: sphinx
Requires-Dist: sphinx-rtd-theme
Provides-Extra: test
Requires-Dist: flake8 ; extra == 'test'
Requires-Dist: flake8-blind-except ; extra == 'test'
Requires-Dist: flake8-builtins ; extra == 'test'
Requires-Dist: flake8-class-newline ; extra == 'test'
Requires-Dist: flake8-comprehensions ; extra == 'test'
Requires-Dist: flake8-deprecated ; extra == 'test'
Requires-Dist: flake8-docstrings ; extra == 'test'
Requires-Dist: flake8-import-order ; extra == 'test'
Requires-Dist: flake8-quotes ; extra == 'test'
Requires-Dist: pytest ; extra == 'test'
